{
  "info": {
    "_postman_id": "0d6b3b1d-identity-service",
    "name": "CanTelcoX - Customer Identity Service",
    "schema": "https://schema.getpostman.com/json/collection/v2.1.0/collection.json",
    "_exporter_id": "6052895"
  },
  "item": [
    {
      "name": "/health",
      "request": {
        "method": "GET",
        "header": [],
        "url": {
          "raw": "{{baseURL}}/health",
          "host": ["{{baseURL}}"],
          "path": ["health"]
        }
      },
      "response": []
    },
    {
      "name": "/customers/register",
      "request": {
        "method": "POST",
        "header": [],
        "body": {
          "mode": "raw",
          "raw": "{\n    \"first_name\": \"John\",\n    \"last_name\": \"Doe\",\n    \"email\": \"john@example.com\",\n    \"phone_number\": \"5145551234\"\n}",
          "options": {
            "raw": {
              "language": "json"
            }
          }
        },
        "url": {
          "raw": "{{baseURL}}/v1/customers/register",
          "host": ["{{baseURL}}"],
          "path": ["v1", "customers", "register"]
        }
      },
      "response": []
    },
    {
      "name": "/customers/:id",
      "request": {
        "method": "GET",
        "header": [],
        "url": {
          "raw": "{{baseURL}}/v1/customers/1",
          "host": ["{{baseURL}}"],
          "path": ["v1", "customers", "1"]
        }
      },
      "response": []
    },
    {
      "name": "/auth/mfa/request",
      "request": {
        "method": "POST",
        "header": [],
        "body": {
          "mode": "raw",
          "raw": "{\n    \"email\": \"john@example.com\"\n}",
          "options": {
            "raw": {
              "language": "json"
            }
          }
        },
        "url": {
          "raw": "{{baseURL}}/v1/auth/mfa/request",
          "host": ["{{baseURL}}"],
          "path": ["v1", "auth", "mfa", "request"]
        }
      },
      "response": []
    },
    {
      "name": "/auth/mfa/verify",
      "request": {
        "method": "POST",
        "header": [],
        "body": {
          "mode": "raw",
          "raw": "{\n    \"email\": \"john@example.com\",\n    \"otp\": \"123456\"\n}",
          "options": {
            "raw": {
              "language": "json"
            }
          }
        },
        "url": {
          "raw": "{{baseURL}}/v1/auth/mfa/verify",
          "host": ["{{baseURL}}"],
          "path": ["v1", "auth", "mfa", "verify"]
        }
      },
      "response": []
    },
    {
      "name": "/metrics",
      "request": {
        "method": "GET",
        "header": [],
        "url": {
          "raw": "{{baseURL}}/metrics",
          "host": ["{{baseURL}}"],
          "path": ["metrics"]
        }
      },
      "response": []
    }
  ],
  "event": [
    {
      "listen": "prerequest",
      "script": {
        "type": "text/javascript",
        "exec": [""]
      }
    },
    {
      "listen": "test",
      "script": {
        "type": "text/javascript",
        "exec": [""]
      }
    }
  ],
  "variable": [
    {
      "key": "baseURL",
      "value": "localhost:5001"
    }
  ]
}
